vdv2pg/__init__.py
vdv2pg/apply_constraints.sql
vdv2pg/parser.py
vdv2pg-0.0.2.dist-info/LICENSE
vdv2pg-0.0.2.dist-info/METADATA
vdv2pg-0.0.2.dist-info/WHEEL
vdv2pg-0.0.2.dist-info/entry_points.txt
vdv2pg-0.0.2.dist-info/top_level.txt
vdv2pg-0.0.2.dist-info/RECORD
