Metadata-Version: 2.1
Name: vdv2pg
Version: 0.0.2
Summary: Import VDV 451 files into a database
Home-page: https://github.com/geops/vdv2pg
Author: Milan Oberkirch | geOps
Author-email: milan.oberkirch@geops.de
License: MIT
Keywords: vdv2pg sql database
Platform: UNKNOWN
Classifier: Programming Language :: Python :: 2.7
Classifier: Programming Language :: Python :: 3
Classifier: Programming Language :: Python
Classifier: License :: OSI Approved :: MIT License
Requires-Dist: SQLAlchemy (==1.2.15)
Requires-Dist: psycopg2-binary (==2.7.6.1)
